hatch_pex/__init__.py
hatch_pex/builder.py
hatch_pex/hooks.py
hatch_pex/util.py
hatch_pex-0.1.3.dist-info/METADATA
hatch_pex-0.1.3.dist-info/WHEEL
hatch_pex-0.1.3.dist-info/entry_points.txt
hatch_pex-0.1.3.dist-info/licenses/LICENSE
hatch_pex-0.1.3.dist-info/RECORD
