Metadata-Version: 2.4
Name: hatch-pex
Version: 0.1.3
Summary: Hatch plugin for building PEX binaries.
Project-URL: Homepage, https://github.com/oh-ok/hatch-pex/
Author-email: Kieran Geary <kieran.r.geary@gmail.com>
License: MIT License
License-File: LICENSE
Classifier: Development Status :: 4 - Beta
Classifier: Environment :: Plugins
Classifier: Framework :: Hatch
Classifier: License :: OSI Approved :: MIT License
Classifier: Programming Language :: Python
Classifier: Programming Language :: Python :: 3
Classifier: Programming Language :: Python :: 3.9
Classifier: Programming Language :: Python :: 3.10
Classifier: Programming Language :: Python :: 3.11
Classifier: Programming Language :: Python :: 3.12
Classifier: Programming Language :: Python :: 3.13
Classifier: Programming Language :: Python :: 3.14
Classifier: Topic :: System :: Software Distribution
Classifier: Topic :: Utilities
Requires-Dist: hatchling
Requires-Dist: pex
